nftoot/__init__.py
nftoot/__main__.py
nftoot/faq.py
nftoot-0.3.dist-info/METADATA
nftoot-0.3.dist-info/WHEEL
nftoot-0.3.dist-info/entry_points.txt
nftoot-0.3.dist-info/licenses/LICENCE.md
nftoot-0.3.dist-info/RECORD
