Metadata-Version: 2.1
Name: NFToot
Version: 0.3
Summary: NFToot bot
Project-URL: Homepage, https://github.com/fpom/nftoot
Project-URL: Bug Tracker, https://github.com/fpom/nftoot/issues
Author-email: Franck Pommereau <franck.pommereau@univ-evry.fr>
License-File: LICENCE.md
Classifier: License :: OSI Approved :: MIT License
Classifier: Operating System :: OS Independent
Classifier: Programming Language :: Python :: 3
Requires-Python: >=3.9
